AUTHORS
CODE_OF_CONDUCT.md
CONTRIBUTING.md
CONTRIBUTORS
LICENSE
MANIFEST.in
README.rst
VERSION
requirements.txt
setup.py
src/logging_ldp/__init__.py
src/logging_ldp/formatters.py
src/logging_ldp/handlers.py
src/logging_ldp/schemas.py
src/logging_ldp.egg-info/PKG-INFO
src/logging_ldp.egg-info/SOURCES.txt
src/logging_ldp.egg-info/dependency_links.txt
src/logging_ldp.egg-info/requires.txt
src/logging_ldp.egg-info/top_level.txt
src/logging_ldp.egg-info/zip-safe