Metadata-Version: 1.1
Name: logging-ldp
Version: 0.0.6
Summary: OVH library bundle to send logs on Log Data Platform (LDP)
Home-page: https://github.com/ovh/python-logging-ldp
Author: OVH SAS
Author-email: github@ovh.net
License: BSD
Platform: UNKNOWN
Classifier: Programming Language :: Python
